Workbook

Sheet 00_README
B1: Samsung Electronics Co., Ltd. — Financial Analysis Portfolio
B2: Consolidated financial data & analysis, FY2022–FY2025 (KRW millions unless noted) — source-cited
B4: Purpose | C4: Financial analysis(Financial Portfolio): Raw data, common-size statements, ratio analysis, growth analysis, segment/geographic breakdowns and a dashboard, built from Samsung's official IR disclosures.
B6: Currency | C6: Korean Won (KRW), in millions, as reported in Samsung's audited/reviewed consolidated financial statements, unless a sheet states otherwise (segment/geographic sales are in KRW trillion, matching Samsung's own Facts & Figures disclosure).
B8: Scope | C8: FY2022-FY2025, complete across income statement, balance sheet and cash flow for all four years. The FY2022 balance sheet and cash flow were the hardest to source, they're drawn from the Dec 31, 2022 comparative column inside Samsung's Q1 2023 interim filing (balance sheet) and from Samsung's Korean-language FY2022 annual filing (cash flow), since the English-language annual FY2022 report wasn't found at its usual archive URL in this pass. Both cross-checked cleanly against the income statement (FY2022 net income of KRW 55,654,077 million and year-end cash of KRW 49,680,710 million match across all three source documents).
B10: Conventions | C10: Blue text = hardcoded source data (input, cell comment shows exact source). Black text = formula computed on the same sheet. Green text = formula linking to another sheet. All ratios use year-end (not average) balances for consistency across all four years.
B12: Workbook map | C12: 01_Income_Statement · 02_Balance_Sheet · 03_Cash_Flow · 04_Segment_Analysis · 05_Geographic_Analysis · 06_Common_Size · 07_Ratios · 08_Growth_Analysis · 09_Dashboard
B15: Source documents used
B16: • Samsung Electronics — Consolidated Financial Statements, December 31, 2024 and 2023 (audited), https://images.samsung.com/is/content/samsung/assets/global/ir/docs/2025_SEC_Consolidated_Financial_statements.pdf
B17: • Samsung Electronics — Consolidated Statements of Financial Position / Profit or Loss / Cash Flows, Dec 31, 2025 and 2024, https://images.samsung.com/is/content/samsung/assets/global/ir/docs/2025_con_quarter04_bs.pdf, _soi.pdf, _cf.pdf
B18: • Samsung Electronics — Consolidated Statements of Profit or Loss, December 31, 2022 and 2021 (audited), https://images.samsung.com/is/content/samsung/assets/global/ir/docs/2022_con_quarter04_soi_1.pdf
B19: • Samsung Electronics — Interim Consolidated Financial Statements, March 31 2023 and 2022 (Dec 31, 2022 balance sheet comparative column, audited), https://images.samsung.com/is/content/samsung/assets/global/ir/docs/2023_con_quarter01_all.pdf
B20: • Samsung Electronics — Consolidated Statements of Cash Flows (Korean), FY2022 and FY2021, https://images.samsung.com/kdp/ir/financial-info/2022/2022_con_quarter04_cf.pdf
B21: • Samsung Electronics — Sustainability 'Facts & Figures' (Sales by Division, Sales by Region), https://www.samsung.com/global/sustainability/digital-library/facts-figures/

Sheet 01_Income_Statement
B1: Consolidated Income Statement
B2: KRW millions, as reported. Source: Samsung audited/reviewed consolidated financial statements.
B4: Line item | C4: 2022 | D4: 2023 | E4: 2024 | F4: 2025 | G4: Unit
B5: Revenue | C5: 302231360 | D5: 258935494 | E5: 300870903 | F5: 333605938 | G5: KRW millions
B6: Cost of sales | C6: 190041770 | D6: 180388580 | E6: 186562268 | F6: 202235513 | G6: KRW millions
B7: Gross profit | C7: 112189590 | D7: 78546914 | E7: 114308635 | F7: 131370425 | G7: KRW millions
B8: Selling & admin. expenses (OpEx) | C8: 68812960 | D8: 71979938 | E8: 81582674 | F8: 87769374 | G8: KRW millions
B9: Operating profit | C9: 43376630 | D9: 6566976 | E9: 32725961 | F9: 43601051 | G9: KRW millions
B10: Profit for the year (Net income) | C10: 55654077 | D10: 15487100 | E10: 34451351 | F10: 45206805 | G10: KRW millions
B13: Raw-data table (KRW trillion)
B14: Year | C14: Revenue | D14: COGS | E14: Gross Profit | F14: OpEx | G14: Operating Profit | H14: Net Income
B15: 2022 | C15: =C5/1000000 -> 302.23136 | D15: =C6/1000000 -> 190.04177 | E15: =C7/1000000 -> 112.18959 | F15: =C8/1000000 -> 68.81296 | G15: =C9/1000000 -> 43.37663 | H15: =C10/1000000 -> 55.654077
B16: 2023 | C16: =D5/1000000 -> 258.93549 | D16: =D6/1000000 -> 180.38858 | E16: =D7/1000000 -> 78.546914 | F16: =D8/1000000 -> 71.979938 | G16: =D9/1000000 -> 6.566976 | H16: =D10/1000000 -> 15.4871
B17: 2024 | C17: =E5/1000000 -> 300.8709 | D17: =E6/1000000 -> 186.56227 | E17: =E7/1000000 -> 114.30863 | F17: =E8/1000000 -> 81.582674 | G17: =E9/1000000 -> 32.725961 | H17: =E10/1000000 -> 34.451351
B18: 2025 | C18: =F5/1000000 -> 333.60594 | D18: =F6/1000000 -> 202.23551 | E18: =F7/1000000 -> 131.37043 | F18: =F8/1000000 -> 87.769374 | G18: =F9/1000000 -> 43.601051 | H18: =F10/1000000 -> 45.206805

Sheet 02_Balance_Sheet
B1: Consolidated Balance Sheet
B2: KRW millions, as of December 31 each year. Source: Samsung audited/reviewed consolidated financial statements.
B4: Line item | C4: 2022 | D4: 2023 | E4: 2024 | F4: 2025 | G4: Unit
B5: Total current assets | C5: 218470581 | D5: 195936557 | E5: 227062266 | F5: 247684612 | G5: KRW millions
B6: Cash and cash equivalents | C6: 49680710 | D6: 69080893 | E6: 53705579 | F6: 57856378 | G6: KRW millions
B7: Trade receivables | C7: 35721563 | D7: 36647393 | E7: 43623073 | F7: 51127642 | G7: KRW millions
B8: Inventories | C8: 52187866 | D8: 51625874 | E8: 51754865 | F8: 52636828 | G8: KRW millions
B9: Total non-current assets | C9: 229953926 | D9: 259969423 | E9: 287469682 | F9: 319257498 | G9: KRW millions
B10: Total assets | C10: 448424507 | D10: 455905980 | E10: 514531948 | F10: 566942110 | G10: KRW millions
B11: Total current liabilities | C11: 78344852 | D11: 75719452 | E11: 93326299 | F11: 106411348 | G11: KRW millions
B12: Total non-current liabilities | C12: 15330051 | D12: 16508663 | E12: 19013579 | F12: 24210425 | G12: KRW millions
B13: Total liabilities | C13: 93674903 | D13: 92228115 | E13: 112339878 | F13: 130621773 | G13: KRW millions
B14: Total equity | C14: 354749604 | D14: 363677865 | E14: 402192070 | F14: 436320337 | G14: KRW millions

Sheet 03_Cash_Flow
B1: Consolidated Cash Flow Statement
B2: KRW millions, for the year ended December 31. Source: Samsung audited/reviewed consolidated financial statements.
B4: Line item | C4: 2022 | D4: 2023 | E4: 2024 | F4: 2025 | G4: Unit
B5: Net cash provided by operating activities | C5: 62181346 | D5: 44137427 | E5: 72982621 | F5: 85315148 | G5: KRW millions
B6: Net cash used in investing activities | C6: -31602804 | D6: -16922817 | E6: -85381702 | F6: -68512206 | G6: KRW millions
B7: Acquisition of property, plant & equipment (Capex) | C7: -49430428 | D7: -57611292 | E7: -51406355 | F7: -47522179 | G7: KRW millions
B8: Net cash used in financing activities | C8: -19390049 | D8: -8593059 | E8: -7797243 | F8: -13478040 | G8: KRW millions
B9: Cash and cash equivalents, end of year | C9: 49680710 | D9: 69080893 | E9: 53705579 | F9: 57856378 | G9: KRW millions
B11: Free Cash Flow (Operating CF − Capex) | C11: =C5+C7 -> 12750918 | D11: =D5+D7 -> -13473865 | E11: =E5+E7 -> 21576266 | F11: =F5+F7 -> 37792969 | G11: KRW millions

Sheet 04_Segment_Analysis
B1: Business Segment Sales Revenue
B2: KRW trillion, net sales by division. Source: Samsung Sustainability 'Facts & Figures'.
B4: Division | C4: 2022 | D4: 2023 | E4: 2024 | F4: 2025 | G4: Unit
B5: DX Division | C5: =182489720/1000000 -> 182.48972 | D5: 170 | E5: 174.9 | F5: 188 | G5: KRW trillion
B6: DS Division | C6: =98455270/1000000 -> 98.45527 | D6: 66.6 | E6: 111.1 | F6: 130.1 | G6: KRW trillion
B7: SDC | C7: =34382619/1000000 -> 34.382619 | D7: 31 | E7: 29.2 | F7: 29.8 | G7: KRW trillion
B8: Harman | C8: =13213694/1000000 -> 13.213694 | D8: 14.4 | E8: 14.3 | F8: 15.8 | G8: KRW trillion
B9: Total (sum of divisions) | C9: =SUM(C5:C8) -> 328.5413 | D9: =SUM(D5:D8) -> 282 | E9: =SUM(E5:E8) -> 329.5 | F9: =SUM(F5:F8) -> 363.7
B11: Segment mix (% of total sales revenue)
B12: Division | C12: 2022 | D12: 2023 | E12: 2024 | F12: 2025
B13: DX Division | C13: =C5/C9 -> 0.55545442 | D13: =D5/D9 -> 0.60283688 | E13: =E5/E9 -> 0.53080425 | F13: =F5/F9 -> 0.51690954
B14: DS Division | C14: =C6/C9 -> 0.29967395 | D14: =D6/D9 -> 0.23617021 | E14: =E6/E9 -> 0.33717754 | F14: =F6/F9 -> 0.3577124
B15: SDC | C15: =C7/C9 -> 0.10465235 | D15: =D7/D9 -> 0.10992908 | E15: =E7/E9 -> 0.08861912 | F15: =F7/F9 -> 0.081935661
B16: Harman | C16: =C8/C9 -> 0.040219278 | D16: =D8/D9 -> 0.05106383 | E16: =E8/E9 -> 0.04339909 | F16: =F8/F9 -> 0.043442398

Sheet 05_Geographic_Analysis
B1: Sales by Region
B2: KRW trillion, net sales by region. Source: Samsung Sustainability 'Facts & Figures'.
B4: Region | C4: 2022 | D4: 2023 | E4: 2024 | F4: 2025 | G4: Unit
B5: Americas | C5: 118.9 | D5: 92.1 | E5: 118.8 | F5: 133.3 | G5: KRW trillion
B6: Europe | C6: 50.2 | D6: 48.1 | E6: 50.1 | F6: 53.3 | G6: KRW trillion
B7: Korea | C7: 48.6 | D7: 45.6 | E7: 39.8 | F7: 46.6 | G7: KRW trillion
B8: Asia and Africa | C8: 48.6 | D8: 73.1 | E8: 92.1 | F8: 100.4 | G8: KRW trillion
B9: Total (sum of regions) | C9: =SUM(C5:C8) -> 266.3 | D9: =SUM(D5:D8) -> 258.9 | E9: =SUM(E5:E8) -> 300.8 | F9: =SUM(F5:F8) -> 333.6
B11: Regional mix (% of total sales)
B12: Region | C12: 2022 | D12: 2023 | E12: 2024 | F12: 2025
B13: Americas | C13: =C5/C9 -> 0.44648892 | D13: =D5/D9 -> 0.35573581 | E13: =E5/E9 -> 0.39494681 | F13: =F5/F9 -> 0.39958034
B14: Europe | C14: =C6/C9 -> 0.1885092 | D14: =D6/D9 -> 0.18578602 | E14: =E6/E9 -> 0.16655585 | F14: =F6/F9 -> 0.15977218
B15: Korea | C15: =C7/C9 -> 0.18250094 | D15: =D7/D9 -> 0.17612978 | E15: =E7/E9 -> 0.13231383 | F15: =F7/F9 -> 0.13968825
B16: Asia and Africa | C16: =C8/C9 -> 0.18250094 | D16: =D8/D9 -> 0.2823484 | E16: =E8/E9 -> 0.30618351 | F16: =F8/F9 -> 0.30095923

Sheet 06_Common_Size
B1: Common-Size Income Statement
B2: Each line item as a percentage of Revenue. All values are formulas referencing 01_Income_Statement.
B4: Line item | C4: 2022 | D4: 2023 | E4: 2024 | F4: 2025
B5: Revenue | C5: ='01_Income_Statement'!C5/'01_Income_Statement'!C5 -> 1 | D5: ='01_Income_Statement'!D5/'01_Income_Statement'!D5 -> 1 | E5: ='01_Income_Statement'!E5/'01_Income_Statement'!E5 -> 1 | F5: ='01_Income_Statement'!F5/'01_Income_Statement'!F5 -> 1
B6: Cost of sales | C6: ='01_Income_Statement'!C6/'01_Income_Statement'!C5 -> 0.62879567 | D6: ='01_Income_Statement'!D6/'01_Income_Statement'!D5 -> 0.69665451 | E6: ='01_Income_Statement'!E6/'01_Income_Statement'!E5 -> 0.62007415 | F6: ='01_Income_Statement'!F6/'01_Income_Statement'!F5 -> 0.60621077
B7: Gross profit | C7: ='01_Income_Statement'!C7/'01_Income_Statement'!C5 -> 0.37120433 | D7: ='01_Income_Statement'!D7/'01_Income_Statement'!D5 -> 0.30334549 | E7: ='01_Income_Statement'!E7/'01_Income_Statement'!E5 -> 0.37992585 | F7: ='01_Income_Statement'!F7/'01_Income_Statement'!F5 -> 0.39378923
B8: Selling & admin. expenses (OpEx) | C8: ='01_Income_Statement'!C8/'01_Income_Statement'!C5 -> 0.22768306 | D8: ='01_Income_Statement'!D8/'01_Income_Statement'!D5 -> 0.27798405 | E8: ='01_Income_Statement'!E8/'01_Income_Statement'!E5 -> 0.27115508 | F8: ='01_Income_Statement'!F8/'01_Income_Statement'!F5 -> 0.26309296
B9: Operating profit | C9: ='01_Income_Statement'!C9/'01_Income_Statement'!C5 -> 0.14352127 | D9: ='01_Income_Statement'!D9/'01_Income_Statement'!D5 -> 0.025361436 | E9: ='01_Income_Statement'!E9/'01_Income_Statement'!E5 -> 0.10877077 | F9: ='01_Income_Statement'!F9/'01_Income_Statement'!F5 -> 0.13069627
B10: Profit for the year (Net income) | C10: ='01_Income_Statement'!C10/'01_Income_Statement'!C5 -> 0.18414395 | D10: ='01_Income_Statement'!D10/'01_Income_Statement'!D5 -> 0.059810649 | E10: ='01_Income_Statement'!E10/'01_Income_Statement'!E5 -> 0.11450543 | F10: ='01_Income_Statement'!F10/'01_Income_Statement'!F5 -> 0.13550959
B12: Reading this: Samsung's cost structure loosened sharply in FY2023 (gross margin fell to ~30% as memory prices collapsed) before recovering through FY2024–FY2025.

Sheet 07_Ratios
B1: Ratio Analysis
B2: Profitability, liquidity, leverage and efficiency ratios. Formulas reference 01_Income_Statement, 02_Balance_Sheet and 03_Cash_Flow.
B4: Metric | C4: 2022 | D4: 2023 | E4: 2024 | F4: 2025
B5: Profitability
B6: Gross margin | C6: ='01_Income_Statement'!C7/'01_Income_Statement'!C5 -> 0.37120433 | D6: ='01_Income_Statement'!D7/'01_Income_Statement'!D5 -> 0.30334549 | E6: ='01_Income_Statement'!E7/'01_Income_Statement'!E5 -> 0.37992585 | F6: ='01_Income_Statement'!F7/'01_Income_Statement'!F5 -> 0.39378923
B7: Operating margin | C7: ='01_Income_Statement'!C9/'01_Income_Statement'!C5 -> 0.14352127 | D7: ='01_Income_Statement'!D9/'01_Income_Statement'!D5 -> 0.025361436 | E7: ='01_Income_Statement'!E9/'01_Income_Statement'!E5 -> 0.10877077 | F7: ='01_Income_Statement'!F9/'01_Income_Statement'!F5 -> 0.13069627
B8: Net margin | C8: ='01_Income_Statement'!C10/'01_Income_Statement'!C5 -> 0.18414395 | D8: ='01_Income_Statement'!D10/'01_Income_Statement'!D5 -> 0.059810649 | E8: ='01_Income_Statement'!E10/'01_Income_Statement'!E5 -> 0.11450543 | F8: ='01_Income_Statement'!F10/'01_Income_Statement'!F5 -> 0.13550959
B9: Return on assets (Net income / Total assets) | C9: ='01_Income_Statement'!C10/'02_Balance_Sheet'!C10 -> 0.12411025 | D9: ='01_Income_Statement'!D10/'02_Balance_Sheet'!D10 -> 0.033969943 | E9: ='01_Income_Statement'!E10/'02_Balance_Sheet'!E10 -> 0.06695668 | F9: ='01_Income_Statement'!F10/'02_Balance_Sheet'!F10 -> 0.079737956
B10: Return on equity (Net income / Total equity) | C10: ='01_Income_Statement'!C10/'02_Balance_Sheet'!C14 -> 0.1568827 | D10: ='01_Income_Statement'!D10/'02_Balance_Sheet'!D14 -> 0.042584665 | E10: ='01_Income_Statement'!E10/'02_Balance_Sheet'!E14 -> 0.085658951 | F10: ='01_Income_Statement'!F10/'02_Balance_Sheet'!F14 -> 0.10360921
B12: Liquidity
B13: Current ratio (Current assets / Current liabilities) | C13: ='02_Balance_Sheet'!C5/'02_Balance_Sheet'!C11 -> 2.7885761 | D13: ='02_Balance_Sheet'!D5/'02_Balance_Sheet'!D11 -> 2.5876648 | E13: ='02_Balance_Sheet'!E5/'02_Balance_Sheet'!E11 -> 2.4329934 | F13: ='02_Balance_Sheet'!F5/'02_Balance_Sheet'!F11 -> 2.3276146
B14: Quick ratio ((Current assets − Inventories) / Current liabilities) | C14: =('02_Balance_Sheet'!C5-'02_Balance_Sheet'!C8)/'02_Balance_Sheet'!C11 -> 2.122446 | D14: =('02_Balance_Sheet'!D5-'02_Balance_Sheet'!D8)/'02_Balance_Sheet'!D11 -> 1.9058601 | E14: =('02_Balance_Sheet'!E5-'02_Balance_Sheet'!E8)/'02_Balance_Sheet'!E11 -> 1.8784352 | F14: =('02_Balance_Sheet'!F5-'02_Balance_Sheet'!F8)/'02_Balance_Sheet'!F11 -> 1.8329604
B16: Leverage
B17: Debt-to-assets (Total liabilities / Total assets) | C17: ='02_Balance_Sheet'!C13/'02_Balance_Sheet'!C10 -> 0.20889782 | D17: ='02_Balance_Sheet'!D13/'02_Balance_Sheet'!D10 -> 0.20229635 | E17: ='02_Balance_Sheet'!E13/'02_Balance_Sheet'!E10 -> 0.21833412 | F17: ='02_Balance_Sheet'!F13/'02_Balance_Sheet'!F10 -> 0.23039702
B18: Debt-to-equity (Total liabilities / Total equity) | C18: ='02_Balance_Sheet'!C13/'02_Balance_Sheet'!C14 -> 0.26405922 | D18: ='02_Balance_Sheet'!D13/'02_Balance_Sheet'!D14 -> 0.25359837 | E18: ='02_Balance_Sheet'!E13/'02_Balance_Sheet'!E14 -> 0.27931898 | F18: ='02_Balance_Sheet'!F13/'02_Balance_Sheet'!F14 -> 0.29937127
B20: Efficiency
B21: Asset turnover (Revenue / Total assets, year-end) | C21: ='01_Income_Statement'!C5/'02_Balance_Sheet'!C10 -> 0.67398493 | D21: ='01_Income_Statement'!D5/'02_Balance_Sheet'!D10 -> 0.5679581 | E21: ='01_Income_Statement'!E5/'02_Balance_Sheet'!E10 -> 0.58474679 | F21: ='01_Income_Statement'!F5/'02_Balance_Sheet'!F10 -> 0.58843034
B22: Inventory turnover (COGS / Inventory, year-end) | C22: ='01_Income_Statement'!C6/'02_Balance_Sheet'!C8 -> 3.6414934 | D22: ='01_Income_Statement'!D6/'02_Balance_Sheet'!D8 -> 3.4941506 | E22: ='01_Income_Statement'!E6/'02_Balance_Sheet'!E8 -> 3.6047291 | F22: ='01_Income_Statement'!F6/'02_Balance_Sheet'!F8 -> 3.8420916
B23: Receivables turnover (Revenue / Trade receivables, year-end) | C23: ='01_Income_Statement'!C5/'02_Balance_Sheet'!C7 -> 8.4607541 | D23: ='01_Income_Statement'!D5/'02_Balance_Sheet'!D7 -> 7.0655911 | E23: ='01_Income_Statement'!E5/'02_Balance_Sheet'!E7 -> 6.8970589 | F23: ='01_Income_Statement'!F5/'02_Balance_Sheet'!F7 -> 6.5249623

Sheet 08_Growth_Analysis
B1: Growth Analysis (Year-over-Year)
B2: Formulas referencing 01_Income_Statement, 02_Balance_Sheet, 03_Cash_Flow and 04_Segment_Analysis.
B4: Metric | C4: 2022 | D4: 2023 | E4: 2024 | F4: 2025
B5: Income statement growth
B6: Revenue growth | C6: n/a | D6: =('01_Income_Statement'!D5-'01_Income_Statement'!C5)/'01_Income_Statement'!C5 -> -0.14325405 | E6: =('01_Income_Statement'!E5-'01_Income_Statement'!D5)/'01_Income_Statement'!D5 -> 0.16195311 | F6: =('01_Income_Statement'!F5-'01_Income_Statement'!E5)/'01_Income_Statement'!E5 -> 0.10880093
B7: Gross profit growth | C7: n/a | D7: =('01_Income_Statement'!D7-'01_Income_Statement'!C7)/'01_Income_Statement'!C7 -> -0.29987342 | E7: =('01_Income_Statement'!E7-'01_Income_Statement'!D7)/'01_Income_Statement'!D7 -> 0.45529123 | F7: =('01_Income_Statement'!F7-'01_Income_Statement'!E7)/'01_Income_Statement'!E7 -> 0.14926073
B8: Operating profit growth | C8: n/a | D8: =('01_Income_Statement'!D9-'01_Income_Statement'!C9)/'01_Income_Statement'!C9 -> -0.84860567 | E8: =('01_Income_Statement'!E9-'01_Income_Statement'!D9)/'01_Income_Statement'!D9 -> 3.9834141 | F8: =('01_Income_Statement'!F9-'01_Income_Statement'!E9)/'01_Income_Statement'!E9 -> 0.33230774
B9: Net income growth | C9: n/a | D9: =('01_Income_Statement'!D10-'01_Income_Statement'!C10)/'01_Income_Statement'!C10 -> -0.72172569 | E9: =('01_Income_Statement'!E10-'01_Income_Statement'!D10)/'01_Income_Statement'!D10 -> 1.2245192 | F9: =('01_Income_Statement'!F10-'01_Income_Statement'!E10)/'01_Income_Statement'!E10 -> 0.31219252
B11: Balance sheet growth
B12: Total assets growth | C12: n/a | D12: =('02_Balance_Sheet'!D10-'02_Balance_Sheet'!C10)/'02_Balance_Sheet'!C10 -> 0.016683908 | E12: =('02_Balance_Sheet'!E10-'02_Balance_Sheet'!D10)/'02_Balance_Sheet'!D10 -> 0.12859223 | F12: =('02_Balance_Sheet'!F10-'02_Balance_Sheet'!E10)/'02_Balance_Sheet'!E10 -> 0.10185988
B13: Total equity growth | C13: n/a | D13: =('02_Balance_Sheet'!D14-'02_Balance_Sheet'!C14)/'02_Balance_Sheet'!C14 -> 0.025167783 | E13: =('02_Balance_Sheet'!E14-'02_Balance_Sheet'!D14)/'02_Balance_Sheet'!D14 -> 0.10590198 | F13: =('02_Balance_Sheet'!F14-'02_Balance_Sheet'!E14)/'02_Balance_Sheet'!E14 -> 0.084855644
B15: Segment sales growth (2022 is the base year)
B16: DX Division sales growth | C16: n/a | D16: =('04_Segment_Analysis'!D5-'04_Segment_Analysis'!C5)/'04_Segment_Analysis'!C5 -> -0.068440677 | E16: =('04_Segment_Analysis'!E5-'04_Segment_Analysis'!D5)/'04_Segment_Analysis'!D5 -> 0.028823529 | F16: =('04_Segment_Analysis'!F5-'04_Segment_Analysis'!E5)/'04_Segment_Analysis'!E5 -> 0.074899943
B17: DS Division sales growth | C17: n/a | D17: =('04_Segment_Analysis'!D6-'04_Segment_Analysis'!C6)/'04_Segment_Analysis'!C6 -> -0.32355068 | E17: =('04_Segment_Analysis'!E6-'04_Segment_Analysis'!D6)/'04_Segment_Analysis'!D6 -> 0.66816817 | F17: =('04_Segment_Analysis'!F6-'04_Segment_Analysis'!E6)/'04_Segment_Analysis'!E6 -> 0.1710171
B18: SDC sales growth | C18: n/a | D18: =('04_Segment_Analysis'!D7-'04_Segment_Analysis'!C7)/'04_Segment_Analysis'!C7 -> -0.098381656 | E18: =('04_Segment_Analysis'!E7-'04_Segment_Analysis'!D7)/'04_Segment_Analysis'!D7 -> -0.058064516 | F18: =('04_Segment_Analysis'!F7-'04_Segment_Analysis'!E7)/'04_Segment_Analysis'!E7 -> 0.020547945
B19: Harman sales growth | C19: n/a | D19: =('04_Segment_Analysis'!D8-'04_Segment_Analysis'!C8)/'04_Segment_Analysis'!C8 -> 0.089778528 | E19: =('04_Segment_Analysis'!E8-'04_Segment_Analysis'!D8)/'04_Segment_Analysis'!D8 -> -0.0069444444 | F19: =('04_Segment_Analysis'!F8-'04_Segment_Analysis'!E8)/'04_Segment_Analysis'!E8 -> 0.1048951

Sheet 09_Dashboard
B1: Samsung Electronics — Financial Dashboard
B2: KRW trillion unless noted. All figures link to the source sheets.
B4: Revenue (FY2025) | D4: Operating Profit (FY2025) | F4: Net Income (FY2025) | H4: Net Margin (FY2025)
B5: ='01_Income_Statement'!F5/1000000 -> 333.60594 | D5: ='01_Income_Statement'!F9/1000000 -> 43.601051 | F5: ='01_Income_Statement'!F10/1000000 -> 45.206805 | H5: ='01_Income_Statement'!F10/'01_Income_Statement'!F5 -> 0.13550959
B8: Metric | C8: 2022 | D8: 2023 | E8: 2024 | F8: 2025
B9: Revenue | C9: ='01_Income_Statement'!C5/1000000 -> 302.23136 | D9: ='01_Income_Statement'!D5/1000000 -> 258.93549 | E9: ='01_Income_Statement'!E5/1000000 -> 300.8709 | F9: ='01_Income_Statement'!F5/1000000 -> 333.60594
B10: Gross profit | C10: ='01_Income_Statement'!C7/1000000 -> 112.18959 | D10: ='01_Income_Statement'!D7/1000000 -> 78.546914 | E10: ='01_Income_Statement'!E7/1000000 -> 114.30863 | F10: ='01_Income_Statement'!F7/1000000 -> 131.37043
B11: Operating profit | C11: ='01_Income_Statement'!C9/1000000 -> 43.37663 | D11: ='01_Income_Statement'!D9/1000000 -> 6.566976 | E11: ='01_Income_Statement'!E9/1000000 -> 32.725961 | F11: ='01_Income_Statement'!F9/1000000 -> 43.601051
B12: Net income | C12: ='01_Income_Statement'!C10/1000000 -> 55.654077 | D12: ='01_Income_Statement'!D10/1000000 -> 15.4871 | E12: ='01_Income_Statement'!E10/1000000 -> 34.451351 | F12: ='01_Income_Statement'!F10/1000000 -> 45.206805
B14: Margin | C14: 2022 | D14: 2023 | E14: 2024 | F14: 2025
B15: Gross margin | C15: ='01_Income_Statement'!C7/'01_Income_Statement'!C5 -> 0.37120433 | D15: ='01_Income_Statement'!D7/'01_Income_Statement'!D5 -> 0.30334549 | E15: ='01_Income_Statement'!E7/'01_Income_Statement'!E5 -> 0.37992585 | F15: ='01_Income_Statement'!F7/'01_Income_Statement'!F5 -> 0.39378923
B16: Operating margin | C16: ='01_Income_Statement'!C9/'01_Income_Statement'!C5 -> 0.14352127 | D16: ='01_Income_Statement'!D9/'01_Income_Statement'!D5 -> 0.025361436 | E16: ='01_Income_Statement'!E9/'01_Income_Statement'!E5 -> 0.10877077 | F16: ='01_Income_Statement'!F9/'01_Income_Statement'!F5 -> 0.13069627
B17: Net margin | C17: ='01_Income_Statement'!C10/'01_Income_Statement'!C5 -> 0.18414395 | D17: ='01_Income_Statement'!D10/'01_Income_Statement'!D5 -> 0.059810649 | E17: ='01_Income_Statement'!E10/'01_Income_Statement'!E5 -> 0.11450543 | F17: ='01_Income_Statement'!F10/'01_Income_Statement'!F5 -> 0.13550959
B19: Division | C19: 2022 | D19: 2023 | E19: 2024 | F19: 2025
B20: DX Division | C20: ='04_Segment_Analysis'!C5 -> 182.48972 | D20: ='04_Segment_Analysis'!D5 -> 170 | E20: ='04_Segment_Analysis'!E5 -> 174.9 | F20: ='04_Segment_Analysis'!F5 -> 188
B21: DS Division | C21: ='04_Segment_Analysis'!C6 -> 98.45527 | D21: ='04_Segment_Analysis'!D6 -> 66.6 | E21: ='04_Segment_Analysis'!E6 -> 111.1 | F21: ='04_Segment_Analysis'!F6 -> 130.1
B22: SDC | C22: ='04_Segment_Analysis'!C7 -> 34.382619 | D22: ='04_Segment_Analysis'!D7 -> 31 | E22: ='04_Segment_Analysis'!E7 -> 29.2 | F22: ='04_Segment_Analysis'!F7 -> 29.8
B23: Harman | C23: ='04_Segment_Analysis'!C8 -> 13.213694 | D23: ='04_Segment_Analysis'!D8 -> 14.4 | E23: ='04_Segment_Analysis'!E8 -> 14.3 | F23: ='04_Segment_Analysis'!F8 -> 15.8
